pdfmerge2/__init__.py
pdfmerge2/app.py
pdfmerge2/exceptions.py
pdfmerge2/merger.py
pdfmerge2-0.1.2.dist-info/entry_points.txt
pdfmerge2-0.1.2.dist-info/LICENSE
pdfmerge2-0.1.2.dist-info/WHEEL
pdfmerge2-0.1.2.dist-info/METADATA
pdfmerge2-0.1.2.dist-info/RECORD
