Metadata-Version: 2.1
Name: pdfmerge2
Version: 0.1.2
Summary: CLI app that merges PDF files
Home-page: https://github.com/Gasper3/pdf-merger
License: MIT
Keywords: pdf,merge,pdfmerge,3.10
Author: Gasper3
Author-email: trzecik65@gmail.com
Requires-Python: >=3.10,<4.0
Classifier: License :: OSI Approved :: MIT License
Classifier: Programming Language :: Python :: 3
Classifier: Programming Language :: Python :: 3.10
Requires-Dist: PyPDF2 (>=1.27.7,<2.0.0)
Project-URL: Repository, https://github.com/Gasper3/pdf-merger
